[
   {
      "adSpotName":"PlanetMarathi_Android_Banner_Carousel_300x250",
      "adSpotKey":"lt5yh3fr",
      "appLocation":"carousel",
      "appLocationIndex":2,
      "adHeight":250,
      "adWidth":300,
      "type":"display",
      "platform":"android",
      "provider":"jio",
      "adImageURL":"",
      "adRedirect":""
   },
   {
      "adSpotName":"PlanetMarathi_IOS_Banner_Carousel_300x250",
      "adSpotKey":"bpczxd1n",
      "appLocation":"carousel",
      "appLocationIndex":2,
      "adHeight":250,
      "adWidth":300,
      "type":"display",
      "platform":"ios",
      "provider":"jio",
      "adImageURL":"",
      "adRedirect":""
   }
]
